Metadata-Version: 2.1
Name: core-module-text-area-app
Version: 2.19.0
Summary: Text Area module for the parser core project
Home-page: https://github.com/usnistgov/core_module_text_area_app
Author: NIST IT Lab
Author-email: itl_inquiries@nist.gov
License-File: LICENSE.md
